LICENSE.txt
MANIFEST.in
README.md
lyt.md
lyt.py
setup.py
lyt.egg-info/PKG-INFO
lyt.egg-info/SOURCES.txt
lyt.egg-info/dependency_links.txt
lyt.egg-info/entry_points.txt
lyt.egg-info/requires.txt
lyt.egg-info/top_level.txt