Metadata-Version: 1.0
Name: lyt
Version: 0.1
Summary: Simple literate programming in Markdown
Home-page: https://github.com/lamarqua/lyt
Author: Adrien Lamarque
Author-email: ad@lamarque.fr
License: GPLv3
Platform: UNKNOWN
